LICENSE
README.md
hwdata.py
setup.py
hwdata.egg-info/PKG-INFO
hwdata.egg-info/SOURCES.txt
hwdata.egg-info/dependency_links.txt
hwdata.egg-info/top_level.txt