Metadata-Version: 2.1
Name: hwdata
Version: 2.4.1
Summary: Interface to hwdata
Home-page: https://github.com/xsuchy/python-hwdata
Author: Miroslav Suchý
Author-email: msuchy@redhat.com
License: setup.py
License-File: LICENSE
